Workbook

Sheet Inputs
A1: Capstone – Proyecto 1 (5G FWA Rural) | Modelo financiero base
A3: Celdas azules = entradas (editables). Celdas negras = fórmulas.
A5: A. Escenario (uniforme)
A6: Ancho | B6: 20 | C6: km
A7: Alto | B7: 10 | C7: km
A8: Área | B8: =B6*B7 -> 200 | C8: km² | D8: Derivado
A9: Hogares totales | B9: 2400 | C9: hogares
A10: Penetración inicial | B10: 0.3
A11: Suscriptores iniciales | B11: =B9*B10 -> 720 | C11: subs | D11: Derivado
A13: B. Tráfico (BH) y QoS
A14: Throughput objetivo por suscriptor | B14: 20 | C14: Mbps
A15: Concurrencia hora pico (BH) | B15: 0.2
A16: Demanda agregada BH | B16: =B11*B14*B15 -> 2880 | C16: Mbps | D16: Subs iniciales * Mbps * concurrencia
A18: C. Resultados técnicos (copiar desde notebook)
A19: Sitios desplegados (S) | B19: 8 | C19: sites | D19: Ingrese el S final de su plan
A20: Cobertura poblacional (fracción) | B20: 0.95666667 | D20: pop_covered_frac (notebook)
A21: Fracción satisfecha capacidad (BH) | B21: 0.98416667 | D21: capacity_satisfied_frac (notebook)
A22: Suscriptores efectivamente servidos | B22: =B11*B21 -> 708.6 | C22: subs | D22: Aprox. subs iniciales * fracción satisfecha
A24: D. Economía (supuestos base)
A25: ARPU (Average Revenue Per User) | B25: 12 | C25: USD/mes
A26: Crecimiento anual de suscriptores | B26: 0.15
A27: Costo instalación por suscriptor | B27: 120 | C27: USD
A28: CAPEX por sitio (radio) | B28: 65000 | C28: USD
A29: CAPEX backhaul por sitio | B29: 12000 | C29: USD
A30: CAPEX adicional si 3 sectores | B30: 18000 | C30: USD
A31: Sitios con 3 sectores (fracción) | B31: 1 | D31: 1.0 = todos 3 sectores
A32: OPEX anual por sitio (radio) | B32: 11000 | C32: USD/año
A33: OPEX anual backhaul por sitio | B33: 3500 | C33: USD/año
A34: Tasa de descuento | B34: 0.1
A35: Horizonte de análisis | B35: 5 | C35: años

Sheet Economics
A1: Proyección financiera (USD)
A3: Concepto | B3: Año 0 | C3: Año 1 | D3: Año 2 | E3: Año 3 | F3: Año 4 | G3: Año 5
A5: Suscriptores servidos (fin de año) | B5: =Inputs!$B$22 -> 708.6 | C5: =B5*(1+Inputs!$B$26) -> 814.89 | D5: =C5*(1+Inputs!$B$26) -> 937.1235 | E5: =D5*(1+Inputs!$B$26) -> 1077.692 | F5: =E5*(1+Inputs!$B$26) -> 1239.3458 | G5: =F5*(1+Inputs!$B$26) -> 1425.2477
A6: Ingresos (ARPU*12) | B6: =B5*Inputs!$B$25*12 -> 102038.4 | C6: =C5*Inputs!$B$25*12 -> 117344.16 | D6: =D5*Inputs!$B$25*12 -> 134945.78 | E6: =E5*Inputs!$B$25*12 -> 155187.65 | F6: =F5*Inputs!$B$25*12 -> 178465.8 | G6: =G5*Inputs!$B$25*12 -> 205235.67
A7: CAPEX sitios (radio + backhaul + sectores) | B7: =+Inputs!B19*(Inputs!B28+Inputs!B29+Inputs!B30) -> 760000 | C7: 0 | D7: 0 | E7: 0 | F7: 0 | G7: 0
A8: CAPEX instalación suscriptores (solo Año 0) | B8: =IF(0=0,B5*Inputs!$B$27,0) -> 85032 | C8: =IF(1=0,C5*Inputs!$B$27,0) -> 0 | D8: =IF(2=0,D5*Inputs!$B$27,0) -> 0 | E8: =IF(3=0,E5*Inputs!$B$27,0) -> 0 | F8: =IF(4=0,F5*Inputs!$B$27,0) -> 0 | G8: =IF(5=0,G5*Inputs!$B$27,0) -> 0
A9: OPEX anual (sitios + backhaul) | B9: 0 | C9: =+Inputs!$B$19*(Inputs!$B$32+Inputs!$B$33) -> 116000 | D9: =+Inputs!$B$19*(Inputs!$B$32+Inputs!$B$33) -> 116000 | E9: =+Inputs!$B$19*(Inputs!$B$32+Inputs!$B$33) -> 116000 | F9: =+Inputs!$B$19*(Inputs!$B$32+Inputs!$B$33) -> 116000 | G9: =+Inputs!$B$19*(Inputs!$B$32+Inputs!$B$33) -> 116000
A10: Flujo de caja neto | B10: =B6-B7-B8-B9 -> -742993.6 | C10: =C6-C7-C8-C9 -> 1344.16 | D10: =D6-D7-D8-D9 -> 18945.784 | E10: =E6-E7-E8-E9 -> 39187.652 | F10: =F6-F7-F8-F9 -> 62465.799 | G10: =G6-G7-G8-G9 -> 89235.669
A11: Factor descuento | B11: =1/(1+Inputs!$B$34)^0 -> 1 | C11: =1/(1+Inputs!$B$34)^1 -> 0.90909091 | D11: =1/(1+Inputs!$B$34)^2 -> 0.82644628 | E11: =1/(1+Inputs!$B$34)^3 -> 0.7513148 | F11: =1/(1+Inputs!$B$34)^4 -> 0.68301346 | G11: =1/(1+Inputs!$B$34)^5 -> 0.62092132
A12: Flujo descontado | B12: =B10*B11 -> -742993.6 | C12: =C10*C11 -> 1221.9636 | D12: =D10*D11 -> 15657.673 | E12: =E10*E11 -> 29442.263 | F12: =F10*F11 -> 42664.981 | G12: =G10*G11 -> 55408.33
A14: KPIs
A15: NPV (USD) | B15: =SUM(B12:G12) -> -598598.39
A16: ROI simple (5 años) | B16: =IF(B7+B8=0,0,SUM(C10:G10)/(B7+B8)) -> 0.24990659
A17: Payback (año) | B17: =Results!B20 -> No hay Payback

Sheet Results
A1: Resultados técnicos + Payback
A3: A. Registro técnico (opcional)
A4: Sitios desplegados | B4: =+Inputs!B19 -> 8
A5: Cobertura poblacional | B5: =+Inputs!B20 -> 0.95666667
A6: Fracción satisfecha BH | B6: =+Inputs!B21 -> 0.98416667
A7: SINR promedio (dB) | B7: 7.6366653
A8: SINR p05 (dB) | B8: -5.9595923
A9: SE promedio (bps/Hz) | B9: 2.7738396
A11: B. Payback (acumulado)
A12: Año | B12: Flujo neto | C12: Acumulado
A13: 0 | B13: =Economics!B10 -> -742993.6 | C13: =B13 -> -742993.6
A14: 1 | B14: =Economics!C10 -> 1344.16 | C14: =C13+B14 -> -741649.44
A15: 2 | B15: =Economics!D10 -> 18945.784 | C15: =C14+B15 -> -722703.66
A16: 3 | B16: =Economics!E10 -> 39187.652 | C16: =C15+B16 -> -683516
A17: 4 | B17: =Economics!F10 -> 62465.799 | C17: =C16+B17 -> -621050.21
A18: 5 | B18: =Economics!G10 -> 89235.669 | C18: =C17+B18 -> -531814.54
A20: Payback (año) | B20: {=IFERROR(INDEX(A13:A18, MATCH(TRUE, C13:C18>=0, 0)), "No hay Payback")} -> No hay Payback
A22: NPV (USD) | B22: =Economics!B15 -> -598598.39
A23: ROI simple (5 años) | B23: =Economics!B16 -> 0.24990659

Sheet Sensitivity
A1: Sensibilidad (manual)
A3: A. Rangos sugeridos (copie a Inputs y observe NPV)
A4: Variable | B4: Bajo | C4: Base (link) | D4: Alto | E4: Nota
A5: ARPU (USD/mes) | B5: 9 | C5: Inputs!$B$25 | D5: 15 | E5: Edite Inputs (azul), luego lea NPV en Economics/Results.
A6: Crecimiento anual subs | B6: 0.03 | C6: Inputs!$B$26 | D6: 0.15 | E6: Edite Inputs (azul), luego lea NPV en Economics/Results.
A7: CAPEX por sitio (USD) | B7: 50000 | C7: Inputs!$B$28 | D7: 85000 | E7: Edite Inputs (azul), luego lea NPV en Economics/Results.
A8: OPEX por sitio/año (USD) | B8: 8000 | C8: Inputs!$B$32 | D8: 16000 | E8: Edite Inputs (azul), luego lea NPV en Economics/Results.
